bocadillo_cli/__init__.py
bocadillo_cli/formatutils.py
bocadillo_cli/main.py
bocadillo_cli/version.py
bocadillo_cli/templates/.gitignore.jinja
bocadillo_cli/templates/README.md.jinja
bocadillo_cli/templates/__init__.py.jinja
bocadillo_cli/templates/app.py.jinja
bocadillo_cli/templates/asgi.py.jinja
bocadillo_cli/templates/providerconf.py.jinja
bocadillo_cli/templates/requirements.txt.jinja
bocadillo_cli/templates/settings.py.jinja
tests/__init__.py
tests/conftest.py
tests/test_basic.py
bocadillo_cli-0.2.2.dist-info/LICENSE
bocadillo_cli-0.2.2.dist-info/METADATA
bocadillo_cli-0.2.2.dist-info/WHEEL
bocadillo_cli-0.2.2.dist-info/entry_points.txt
bocadillo_cli-0.2.2.dist-info/top_level.txt
bocadillo_cli-0.2.2.dist-info/RECORD
