Metadata-Version: 2.1
Name: bocadillo-cli
Version: 0.2.2
Summary: Standard development tooling for Bocadillo
Home-page: https://github.com/bocadilloproject/bocadillo-cli
Author: Florimond Manca
Author-email: florimond.manca@gmail.com
License: MIT
Platform: UNKNOWN
Classifier: Development Status :: 2 - Pre-Alpha
Classifier: Environment :: Console
Classifier: Intended Audience :: Developers
Classifier: License :: OSI Approved :: MIT License
Classifier: Natural Language :: English
Classifier: Operating System :: OS Independent
Classifier: Programming Language :: Python :: 3 :: Only
Classifier: Programming Language :: Python :: 3.6
Classifier: Programming Language :: Python :: 3.7
Classifier: Topic :: Utilities
Classifier: Topic :: Software Development :: Code Generators
Requires-Python: >=3.6
Requires-Dist: click (<8.0,>=7.0)
Requires-Dist: jinja2 (>=2.10.1)
